scrapy_frontera/__init__.py
scrapy_frontera/converters.py
scrapy_frontera/manager.py
scrapy_frontera/middlewares.py
scrapy_frontera/scheduler.py
scrapy_frontera/settings.py
scrapy_frontera/utils.py
scrapy_frontera/components/__init__.py
scrapy_frontera/core/__init__.py
scrapy_frontera/core/manager.py
scrapy_frontera-0.3.0.dist-info/licenses/LICENSE
scrapy_frontera-0.3.0.dist-info/METADATA
scrapy_frontera-0.3.0.dist-info/WHEEL
scrapy_frontera-0.3.0.dist-info/top_level.txt
scrapy_frontera-0.3.0.dist-info/RECORD
