Metadata-Version: 2.4
Name: scrapy-frontera
Version: 0.3.0
Summary: Featured Frontera scheduler for Scrapy
Home-page: https://github.com/scrapinghub/scrapy-frontera
Maintainer: Scrapinghub
License: BSD
Classifier: Development Status :: 5 - Production/Stable
Classifier: Intended Audience :: Developers
Classifier: License :: OSI Approved :: BSD License
Classifier: Operating System :: OS Independent
Classifier: Programming Language :: Python
Classifier: Programming Language :: Python :: 3
Requires-Python: >=3.9
License-File: LICENSE
Requires-Dist: frontera<0.8,>=0.7.2
Requires-Dist: scrapy>=2.7.0
Requires-Dist: w3lib>=1.17.0
Dynamic: classifier
Dynamic: description
Dynamic: home-page
Dynamic: license
Dynamic: license-file
Dynamic: maintainer
Dynamic: requires-dist
Dynamic: requires-python
Dynamic: summary
